{
  "pistol": {
    "name": "ハンドガン",
    "damage": 1,
    "fireRate": 350,
    "bulletSpeed": 280,
    "bulletSize": 5,
    "color": 16768836,
    "range": 1200,
    "spread": 0,
    "magSize": 12,
    "reloadTime": 1200
  },
  "smg": {
    "name": "SMG",
    "damage": 0.8,
    "fireRate": 120,
    "bulletSpeed": 220,
    "bulletSize": 4,
    "color": 16776960,
    "range": 900,
    "spread": 3,
    "magSize": 30,
    "reloadTime": 1400
  },
  "ar": {
    "name": "AR",
    "damage": 1.2,
    "fireRate": 200,
    "bulletSpeed": 320,
    "bulletSize": 5,
    "color": 16777215,
    "range": 1400,
    "spread": 1,
    "magSize": 30,
    "reloadTime": 1500
  },
  "sr": {
    "name": "SR",
    "damage": 2.5,
    "fireRate": 800,
    "bulletSpeed": 450,
    "bulletSize": 6,
    "color": 16711680,
    "range": 2000,
    "spread": 0,
    "magSize": 8,
    "reloadTime": 2000
  },
  "sg": {
    "name": "SG",
    "damage": 0.7,
    "fireRate": 600,
    "bulletSpeed": 200,
    "bulletSize": 4,
    "color": 16776960,
    "range": 400,
    "spread": 25,
    "pellets": 6,
    "magSize": 6,
    "reloadTime": 1800
  }
}
